triplep/__init__.py
triplep/main.py
triplep/models.py
triplep/utils.py
triplep-1.0.1.dist-info/licenses/LICENSE
triplep-1.0.1.dist-info/METADATA
triplep-1.0.1.dist-info/WHEEL
triplep-1.0.1.dist-info/top_level.txt
triplep-1.0.1.dist-info/RECORD
